{"id":"KZMBJP7KSTWVS","name":"二次元国风作品集合-2021UIUI游戏UI小金狮 - 原创作品 - 站酷 ZCOOL","size":691055,"btime":1644820314477,"mtime":1644820314478,"ext":"jpg","tags":[],"folders":["KTMA1TYQXPCUP"],"isDeleted":false,"url":"https://www.zcool.com.cn/work/ZNTY4NDg5MjQ=.html","annotation":"","modificationTime":1650615444301,"height":788,"width":1560,"lastModified":1644820314946,"palettes":[{"color":[30,31,35],"ratio":71},{"color":[232,231,229],"ratio":9},{"color":[62,66,73],"ratio":9},{"color":[66,54,44],"ratio":2.67},{"color":[105,106,110],"ratio":2.66},{"color":[106,88,72],"ratio":1.73},{"color":[186,153,57],"ratio":1.44}]}