{"id":"L39Z3BZ3YNBDN","name":"梦幻西游三维-游戏截图-GAMEUI.NET-游戏UIUX学习、交流、分享平台","size":92993,"btime":1652780930669,"mtime":1652780930673,"ext":"jpg","tags":[],"folders":["L39TTA45456ZF"],"isDeleted":false,"url":"https://gameui.net/inspirationInfo/4270","annotation":"","modificationTime":1652780930655,"height":864,"width":1920,"lastModified":1652780931153,"palettes":[{"color":[126,172,203],"ratio":56},{"color":[230,219,204],"ratio":21},{"color":[183,195,211],"ratio":9},{"color":[194,176,89],"ratio":4.94},{"color":[82,150,188],"ratio":3.46},{"color":[158,174,133],"ratio":1.89},{"color":[128,159,165],"ratio":1.73},{"color":[185,222,162],"ratio":0.46}]}