{"id":"LEFBK1HJBB0EW","name":"《梦幻西游》电脑版2022新春华服大赛专题","size":1979468,"btime":1677048802210,"mtime":1677048802210,"ext":"png","tags":[],"folders":["LE85S3A762AB5"],"isDeleted":false,"url":"https://huaban.com/pins/5314446880","annotation":"","modificationTime":1677048802183,"height":3071,"width":1920,"lastModified":1677048802657,"palettes":[{"color":[55,37,46],"ratio":89},{"color":[78,51,46],"ratio":6},{"color":[66,43,60],"ratio":1.63},{"color":[96,68,52],"ratio":1.13},{"color":[131,97,58],"ratio":0.64},{"color":[219,196,107],"ratio":0.38}]}