{"id":"LCA8459ZSXCVD","name":"crypto-gold_h_card_block_b","size":22040,"btime":1672387091802,"mtime":1672387091802,"ext":"png","tags":[],"folders":["LCKABRN9VHN2Q"],"isDeleted":false,"url":"","annotation":"","modificationTime":1672387143404,"width":350,"height":350,"noThumbnail":true,"lastModified":1672995508628,"palettes":[{"color":[73,194,147],"ratio":38},{"color":[231,250,219],"ratio":26},{"color":[159,239,193],"ratio":12},{"color":[32,159,118],"ratio":5},{"color":[115,219,171],"ratio":5},{"color":[125,239,189],"ratio":4.93},{"color":[21,140,98],"ratio":4.57},{"color":[115,226,189],"ratio":1.46},{"color":[175,252,212],"ratio":0.54},{"color":[54,158,92],"ratio":0.35}]}