{"id":"LDJW3GK89EQR3","name":"SpriteAtlasTexture-homescene_home_pata_mainId_earth_3_a-1024x512-fmt34_out","size":450127,"btime":1689072358362,"mtime":1689072358362,"ext":"png","tags":[],"folders":["LDJW3GIK4Y92N"],"isDeleted":false,"url":"","annotation":"","modificationTime":1675148512475,"noThumbnail":true,"width":1024,"height":512,"lastModified":1689238676675,"palettes":[{"color":[60,168,249],"ratio":43},{"color":[210,212,221],"ratio":24},{"color":[152,169,184],"ratio":10},{"color":[88,235,251],"ratio":9},{"color":[129,125,137],"ratio":3.93},{"color":[62,116,222],"ratio":3.23},{"color":[101,177,230],"ratio":2.1},{"color":[60,79,149],"ratio":1},{"color":[172,164,172],"ratio":0.91},{"color":[172,172,172],"ratio":0.81}]}