{"id":"LAVX3URQHCUG0","name":"grav_pt1_episode_36_bg02","size":145431,"btime":1669516743156,"mtime":1669516743156,"ext":"jpg","tags":[],"folders":["LAVWU5SASGDKW"],"isDeleted":false,"url":"","annotation":"","modificationTime":1669345339922,"height":1450,"width":773,"lastModified":1677748795515,"palettes":[{"color":[130,101,91],"ratio":39},{"color":[223,168,119],"ratio":13},{"color":[233,228,215],"ratio":11},{"color":[232,208,146],"ratio":9},{"color":[41,75,101],"ratio":5},{"color":[165,154,155],"ratio":5},{"color":[179,168,87],"ratio":4.93},{"color":[111,85,29],"ratio":4.36},{"color":[180,122,89],"ratio":3.88},{"color":[84,46,37],"ratio":2.3}]}