{"id":"L2E6V0FAH8VFI","name":"VALORANT Agent Selection Screen UI [For Fun] on Behance","size":1260454,"btime":1650505451244,"mtime":1650505451249,"ext":"png","tags":[],"folders":["L2E6UZKXG2L76"],"isDeleted":false,"url":"https://www.behance.net/gallery/96477133/VALORANT-Agent-Selection-Screen-UI-For-Fun?tracking_source=search_projects_recommended%7Cvalorant","annotation":"","modificationTime":1650859062124,"height":1080,"width":1920,"palettes":[{"color":[23,20,26],"ratio":76},{"color":[60,46,54],"ratio":6},{"color":[195,154,153],"ratio":5},{"color":[108,75,80],"ratio":5},{"color":[230,55,68],"ratio":1.66},{"color":[40,40,56],"ratio":1.62},{"color":[58,69,100],"ratio":1},{"color":[120,118,179],"ratio":0.45}],"lastModified":1650520826731}