{"id":"LCA8459ZHFJ9Y","name":"bali-vacation_l_k","size":32981,"btime":1672387089127,"mtime":1672387089127,"ext":"png","tags":[],"folders":["LCKABRN9VHN2Q"],"isDeleted":false,"url":"","annotation":"","modificationTime":1672387144431,"width":350,"height":350,"noThumbnail":true,"lastModified":1675062973566,"palettes":[{"color":[60,60,65],"ratio":83},{"color":[196,121,106],"ratio":10},{"color":[42,38,36],"ratio":1.47},{"color":[164,92,83],"ratio":1.22},{"color":[141,140,149],"ratio":0.88},{"color":[120,120,128],"ratio":0.81},{"color":[100,100,108],"ratio":0.57}]}