{"id":"LAVX3URPECHB0","name":"grav_pt1_episode13_bg01","size":241610,"btime":1669516743058,"mtime":1669516743058,"ext":"jpg","tags":[],"folders":["LAVWU5SASGDKW"],"isDeleted":false,"url":"","annotation":"","modificationTime":1669345332255,"height":1450,"width":773,"lastModified":1677748796691,"palettes":[{"color":[140,107,94],"ratio":22},{"color":[237,223,212],"ratio":12},{"color":[232,230,138],"ratio":12},{"color":[134,47,48],"ratio":10},{"color":[176,147,162],"ratio":10},{"color":[233,177,130],"ratio":9},{"color":[56,62,57],"ratio":7},{"color":[165,139,31],"ratio":7},{"color":[162,181,75],"ratio":6}]}