{"id":"KSOGUHETR8IYB","name":"robin-tran-lastofus-stylized2","size":1421659,"btime":1629712671696,"mtime":1629712671698,"ext":"jpg","tags":[],"folders":["KLD5E2YWTF4C7"],"isDeleted":false,"url":"https://www.artstation.com/artwork/XnrLAl","annotation":"","modificationTime":1650612635057,"height":1701,"width":3840,"lastModified":1629712672862,"palettes":[{"color":[24,54,45],"ratio":50},{"color":[246,247,248],"ratio":18},{"color":[115,130,110],"ratio":9},{"color":[58,122,94],"ratio":7},{"color":[67,62,47],"ratio":5},{"color":[98,169,186],"ratio":4.87},{"color":[51,99,107],"ratio":2.01},{"color":[162,168,150],"ratio":0.86},{"color":[125,165,134],"ratio":0.65}]}