{"id":"L81GU8GYO7AQ0","name":"杨幂 x《MadameFigaro中文版》六月刊  制片美术 (3)","size":318075,"btime":1663171602228,"mtime":1663171602249,"ext":"jpg","tags":[],"folders":["L77CAHNZEV6HA"],"isDeleted":false,"url":"https://www.zcool.com.cn/work/ZNjAxMTUyNTI=.html","annotation":"","modificationTime":1663150455368,"height":1619,"width":1080,"lastModified":1663171608427,"palettes":[{"color":[136,112,105],"ratio":46},{"color":[208,207,209],"ratio":14},{"color":[173,169,170],"ratio":9},{"color":[31,24,21],"ratio":8},{"color":[169,157,153],"ratio":6},{"color":[86,80,77],"ratio":4.78},{"color":[87,55,45],"ratio":3.83},{"color":[198,189,185],"ratio":2.42},{"color":[207,173,163],"ratio":1.83}]}