{"id":"L75N74YXGC9C1","name":"Newake Free Font","size":656676,"btime":1661226217459,"mtime":1661226217459,"ext":"jpg","tags":[],"folders":["L6W0KMPWN3NY1"],"isDeleted":false,"url":"https://www.behance.net/gallery/118133975/Newake-Free-Font?tracking_source=project_owner_other_projects","annotation":"","modificationTime":1661226217449,"height":1344,"width":1920,"lastModified":1661226217795,"palettes":[{"color":[13,14,16],"ratio":78},{"color":[7,113,214],"ratio":7},{"color":[15,23,38],"ratio":5},{"color":[11,27,58],"ratio":4.35},{"color":[11,46,93],"ratio":2.06},{"color":[16,79,144],"ratio":1.52},{"color":[28,36,39],"ratio":0.35}]}