{"id":"LE8715LNLLWBS","name":"中式传统背景PNG图片","size":318772,"ext":"png","tags":["图案","国风","纹理"],"folders":[],"isDeleted":true,"url":"https://huaban.com/pins/3743879319/","annotation":"","modificationTime":1676617939392,"height":2433,"width":2500,"lastModified":1678175388218,"palettes":[{"color":[152,123,84],"ratio":76},{"color":[148,123,100],"ratio":7},{"color":[164,121,83],"ratio":5},{"color":[140,124,85],"ratio":3.64},{"color":[151,132,85],"ratio":3.24},{"color":[145,124,108],"ratio":1.26},{"color":[154,122,68],"ratio":1.19},{"color":[132,125,85],"ratio":0.33}],"mtime":1654564567616,"btime":1625646955467,"deletedTime":1678175388110}