{"id":"LMOCBN538GXRU","name":"ui扁平类技能图标参考二次元-图标资源-微元素 - Element3ds.com!","size":165790,"btime":1696753187068,"mtime":1696753187068,"ext":"webp","tags":[],"folders":["LMFOMTB76KZZT"],"isDeleted":false,"url":"https://huaban.com/pins/2590691115","annotation":"","modificationTime":1695008544231,"height":675,"width":1200,"noThumbnail":true,"lastModified":1696758771263,"palettes":[{"color":[25,21,45],"ratio":73},{"color":[214,213,217],"ratio":9},{"color":[98,100,116],"ratio":8},{"color":[59,61,81],"ratio":5},{"color":[63,54,62],"ratio":2.04}]}