{"id":"LIA27C5NUJ236","name":"(6) Pinterest","size":242205,"btime":1689072447070,"mtime":1689072447070,"ext":"png","tags":[],"folders":["LMFOMTB76KZZT"],"isDeleted":false,"url":"https://www.pinterest.com/pin/231091024619525708/","annotation":"","modificationTime":1685437891403,"noThumbnail":true,"width":1024,"height":768,"lastModified":1694485115842,"palettes":[{"color":[251,251,251],"ratio":90},{"color":[175,175,175],"ratio":2.62},{"color":[106,106,106],"ratio":2.27},{"color":[196,196,196],"ratio":0.75},{"color":[228,228,228],"ratio":0.69},{"color":[204,204,204],"ratio":0.66},{"color":[212,212,212],"ratio":0.65},{"color":[220,220,220],"ratio":0.65},{"color":[140,140,140],"ratio":0.53},{"color":[156,156,156],"ratio":0.5},{"color":[148,148,148],"ratio":0.43}]}