{"id":"L6X96RKOBNQR4","name":"崩坏3游戏截图","size":192632,"btime":1660718956062,"mtime":1660718956062,"ext":"jpg","tags":["宣传"],"folders":["L6X8Z31UKLU27"],"isDeleted":false,"url":"https://www.taptap.com/app/10056","annotation":"","modificationTime":1660718956056,"noThumbnail":true,"width":1280,"height":720,"palettes":[{"color":[242,242,243],"ratio":43,"$$hashKey":"object:5726"},{"color":[211,142,164],"ratio":23,"$$hashKey":"object:5727"},{"color":[212,181,204],"ratio":8,"$$hashKey":"object:5728"},{"color":[58,45,78],"ratio":6,"$$hashKey":"object:5729"},{"color":[147,207,239],"ratio":6,"$$hashKey":"object:5730"},{"color":[228,170,162],"ratio":3.93,"$$hashKey":"object:5731"},{"color":[171,90,125],"ratio":3.19,"$$hashKey":"object:5732"},{"color":[57,75,148],"ratio":1.88,"$$hashKey":"object:5733"},{"color":[82,128,199],"ratio":1.29,"$$hashKey":"object:5734"},{"color":[105,171,240],"ratio":0.87,"$$hashKey":"object:5735"},{"color":[164,128,96],"ratio":0.72,"$$hashKey":"object:5736"}],"lastModified":1660719951655}