{"id":"LDVAF1H48QRLC","name":"ExEquipImg","size":151242,"btime":1675837565758,"mtime":1675837565759,"ext":"png","tags":[],"folders":["L2D5873BQZEU3"],"isDeleted":false,"url":"https://huaban.com/pins/5297476950","annotation":"","modificationTime":1675837565752,"noThumbnail":true,"width":512,"height":512,"lastModified":1675837978939,"palettes":[{"color":[106,207,171],"ratio":37},{"color":[236,207,127],"ratio":22},{"color":[67,20,21],"ratio":16},{"color":[66,153,134],"ratio":9},{"color":[222,71,86],"ratio":4.25},{"color":[147,102,59],"ratio":3.82},{"color":[72,122,103],"ratio":3.02},{"color":[97,144,108],"ratio":1.16},{"color":[37,127,113],"ratio":0.85},{"color":[157,232,186],"ratio":0.68}]}