{"id":"L2H6SA19SLAPX","name":"王者荣耀活动界面-727","size":237008,"btime":1651038201763,"mtime":1651038693764,"ext":"jpg","tags":[],"folders":["L2H6EFQDFOB6Z"],"isDeleted":true,"url":"","annotation":"","modificationTime":1651040364440,"height":1170,"width":2532,"lastModified":1651804848430,"palettes":[{"color":[19,17,16],"ratio":64},{"color":[101,153,167],"ratio":7},{"color":[202,206,194],"ratio":7},{"color":[110,78,69],"ratio":6},{"color":[66,120,149],"ratio":5},{"color":[53,94,114],"ratio":4.05},{"color":[185,151,104],"ratio":1.99},{"color":[183,112,61],"ratio":1.12},{"color":[157,72,47],"ratio":0.74},{"color":[35,60,87],"ratio":0.62}],"deletedTime":1651804848307}