{"id":"L2LAYSMEHEJXY","name":"iPad 屏幕截图 3","size":73749,"btime":1651719023852,"mtime":1651719023852,"ext":"jpg","tags":[],"folders":["L2E6UZKXFWJEW"],"isDeleted":false,"url":"","annotation":"","modificationTime":1651289254872,"noThumbnail":true,"width":576,"height":768,"lastModified":1666150417927,"palettes":[{"color":[175,60,76],"ratio":40},{"color":[176,22,143],"ratio":17},{"color":[244,227,219],"ratio":11},{"color":[208,134,109],"ratio":9},{"color":[121,43,69],"ratio":8},{"color":[172,48,23],"ratio":3.06},{"color":[216,204,48],"ratio":2.89},{"color":[80,60,80],"ratio":2.74},{"color":[226,86,83],"ratio":1.9},{"color":[213,45,178],"ratio":0.65}]}