{"id":"L2D588QPJZ7OZ","name":"嫦娥","size":9789,"btime":1650811889424,"mtime":1650811889424,"ext":"png","tags":[],"folders":["L2D5873BRDVGR"],"isDeleted":false,"url":"https://huaban.com/pins/4050258712/","annotation":"","modificationTime":1650795854493,"noThumbnail":true,"width":128,"height":128,"lastModified":1651288988397,"palettes":[{"color":[51,57,114],"ratio":32},{"color":[16,23,50],"ratio":14},{"color":[105,125,224],"ratio":12},{"color":[206,218,241],"ratio":10},{"color":[136,141,177],"ratio":7},{"color":[78,93,182],"ratio":7},{"color":[101,103,147],"ratio":7},{"color":[155,180,232],"ratio":4.59},{"color":[108,124,181],"ratio":1.14},{"color":[172,180,212],"ratio":0.69},{"color":[76,95,157],"ratio":0.64}]}