{"id":"L2D587DLWGPBF","name":"63771551490316","size":2094472,"btime":1635926619375,"mtime":1635925891351,"ext":"png","tags":[],"folders":["L2D5873BKTOLA"],"isDeleted":false,"url":"","annotation":"","modificationTime":1650795852082,"height":1080,"width":1920,"lastModified":1635926628208,"palettes":[{"color":[50,56,59],"ratio":65},{"color":[89,89,88],"ratio":15},{"color":[134,121,111],"ratio":8},{"color":[184,178,167],"ratio":6},{"color":[96,123,125],"ratio":1.22},{"color":[19,13,12],"ratio":0.8},{"color":[151,166,163],"ratio":0.59},{"color":[42,29,19],"ratio":0.44},{"color":[81,106,118],"ratio":0.39}]}