{"id":"LDJTECWOZ87HE","name":"ground4","size":34622,"btime":1675174794413,"mtime":1675174794413,"ext":"png","tags":[],"folders":["LDJTECR1UHOT7"],"isDeleted":false,"url":"","annotation":"","modificationTime":1675143938289,"noThumbnail":true,"width":320,"height":107,"lastModified":1708419907567,"palettes":[{"color":[243,194,71],"ratio":21},{"color":[235,147,44],"ratio":21},{"color":[240,175,58],"ratio":15},{"color":[236,158,52],"ratio":14},{"color":[227,127,44],"ratio":11},{"color":[217,112,43],"ratio":8},{"color":[196,92,42],"ratio":3.57},{"color":[237,180,68],"ratio":1.38},{"color":[244,188,60],"ratio":0.93},{"color":[176,109,28],"ratio":0.41}]}