{"id":"LGW1CQR4YFOEB","name":"GIF-egg","size":2033219,"btime":1689072432779,"mtime":1689072432780,"ext":"gif","tags":[],"folders":["LFETRQL0CK1WL"],"isDeleted":false,"url":"https://huaban.com/pins/5037257409","annotation":"","modificationTime":1682413155184,"height":1080,"width":1920,"lastModified":1691042419813,"palettes":[{"color":[172,116,83],"ratio":38},{"color":[236,218,199],"ratio":12},{"color":[195,160,124],"ratio":10},{"color":[222,195,163],"ratio":9},{"color":[226,119,82],"ratio":9},{"color":[213,174,143],"ratio":5},{"color":[185,147,116],"ratio":3.97},{"color":[184,77,43],"ratio":3.86},{"color":[175,65,36],"ratio":3.76},{"color":[119,59,37],"ratio":1.88}]}