{"id":"KNFN69AETI4Z2","name":"万众期待的熊本它来了！《海岛纪元》×熊本熊联动即将开启_看图_海岛纪元吧_百度贴吧","size":285469,"ext":"jpg","tags":[],"folders":["KMLCLAXPCIRHH","KWOEFSKIPHI56"],"isDeleted":false,"url":"https://huaban.com/pins/3617206722/","annotation":"","modificationTime":1650610883957,"noThumbnail":true,"width":900,"height":417,"lastModified":1644220774950,"palettes":[{"color":[140,118,72],"ratio":54},{"color":[229,226,214],"ratio":27},{"color":[159,149,134],"ratio":6},{"color":[98,75,61],"ratio":6},{"color":[183,199,65],"ratio":2.78},{"color":[91,50,84],"ratio":1.56},{"color":[211,149,80],"ratio":0.42},{"color":[156,107,204],"ratio":0.37},{"color":[170,162,54],"ratio":0.33}],"mtime":1618295191441,"btime":1618295191499}