{"id":"L2E6UZLHQA5PU","name":"Luscus game 2018 on Behance (39)","size":944109,"btime":1649731119004,"mtime":1649731119026,"ext":"jpg","tags":[],"folders":["L2E6UZKXFWJEW"],"isDeleted":false,"url":"https://www.behance.net/gallery/62922903/Luscus-game-(2018)","annotation":"","modificationTime":1650859060669,"height":1094,"width":1920,"lastModified":1649731183791,"palettes":[{"color":[101,177,217],"ratio":44},{"color":[26,32,40],"ratio":19},{"color":[220,205,196],"ratio":13},{"color":[164,214,237],"ratio":9},{"color":[31,133,157],"ratio":4.99},{"color":[103,98,83],"ratio":2.53},{"color":[84,110,133],"ratio":2.06},{"color":[223,85,78],"ratio":1.19},{"color":[129,143,141],"ratio":1.11},{"color":[144,221,244],"ratio":1.11}]}