{"id":"LDNY6RR9297W7","name":"king_super_grotesk_offc_pro","size":83928,"btime":1675393719981,"mtime":347130062000,"ext":"ttf","tags":["Regular"],"folders":["LDNY6RQWFBCC4"],"isDeleted":false,"url":"","annotation":"","modificationTime":1675393763862,"height":600,"width":600,"fontMetas":{"copyright":{"en":"2012 Svend Smital published by FSI FontShop International GmbH"},"fontFamily":{"en":"Super Grotesk Offc Pro"},"fontSubfamily":{"en":"Regular"},"uniqueID":{"en":"Svend Smital: Super Grotesk Offc Pro: 2012"},"fullName":{"en":"Super Grotesk Offc Pro"},"version":{"en":"Version 7.504; 2012; Build 1020"},"postScriptName":{"en":"SuperGroteskOffcPro"},"trademark":{"en":"SuperGrotesk is a trademark of FSI FontShop International GmbH"},"manufacturer":{"en":"FSI"},"designer":{"en":"Svend Smital"},"manufacturerURL":{"en":"http://www.fontfont.com"},"designerURL":{"en":"http://www.fontfont.com"},"licenseURL":{"en":"http://www.fontfont.com/eula/license.html"},"preferredFamily":{"en":"Super Grotesk Offc Pro"},"preferredSubfamily":{"en":"Regular"},"numGlyphs":425,"support":{},"weight":"Regular"},"lastModified":1675393765073,"palettes":[{"color":[251,251,251],"ratio":94},{"color":[60,60,60],"ratio":4.31},{"color":[177,177,177],"ratio":0.69}]}