{"id":"L2H8FLT7ODONH","name":"王者荣耀活动界面-488","size":986903,"btime":1651038189368,"mtime":1629276110915,"ext":"jpg","tags":[],"folders":["L2H6EFQDFOB6Z"],"isDeleted":true,"url":"","annotation":"","modificationTime":1651043104405,"noThumbnail":true,"width":1334,"height":750,"orientation":1,"lastModified":1651804849107,"palettes":[{"color":[19,18,21],"ratio":56},{"color":[190,78,52],"ratio":17},{"color":[244,222,171],"ratio":10},{"color":[115,68,63],"ratio":5},{"color":[205,156,125],"ratio":4.11},{"color":[182,167,177],"ratio":2.19},{"color":[167,123,125],"ratio":1.79},{"color":[60,93,78],"ratio":0.55},{"color":[118,155,144],"ratio":0.41},{"color":[127,121,149],"ratio":0.41}],"deletedTime":1651804848307}