{"id":"LG6B8QHCI133X","name":"2023-04-07 16 10 43","size":605257,"btime":1680855043955,"mtime":1680855044236,"ext":"png","tags":[],"folders":["LG6B8LX824ZDS"],"isDeleted":false,"url":"","annotation":"","modificationTime":1680857644152,"noThumbnail":true,"width":1253,"height":710,"lastModified":1680857649249,"palettes":[{"color":[120,116,99],"ratio":55},{"color":[231,236,230],"ratio":26},{"color":[229,207,135],"ratio":5},{"color":[165,163,155],"ratio":4.71},{"color":[172,153,122],"ratio":3.27},{"color":[90,82,37],"ratio":3.07},{"color":[58,65,70],"ratio":1.14},{"color":[181,190,168],"ratio":0.83}]}