{"id":"L2IX2HASA0DIH","name":"Riverbond-1sz3z","size":3822217,"btime":1651144944918,"mtime":1651144951397,"ext":"png","tags":[],"folders":["L2E6UZKXW1ANQ"],"isDeleted":false,"url":"https://store.epicgames.com/en-US/p/riverbond-782aa4","annotation":"","modificationTime":1651144568333,"height":1080,"width":1920,"lastModified":1651144958709,"palettes":[{"color":[99,150,72],"ratio":35},{"color":[93,168,227],"ratio":18},{"color":[121,209,93],"ratio":10},{"color":[154,134,86],"ratio":8},{"color":[83,89,59],"ratio":7},{"color":[64,50,35],"ratio":5},{"color":[114,155,142],"ratio":5},{"color":[37,92,35],"ratio":3.95},{"color":[209,193,205],"ratio":2.97},{"color":[215,142,100],"ratio":2.21}]}