{"id":"KTMAHJZ5LUOC2","name":"欧美暗色卡通二次元GUI界面风格集合UI游戏UI小金狮 - 原创作品 - 站酷 ZCOOL (17)","size":190088,"btime":1650779435264,"mtime":1650779435264,"ext":"jpg","tags":[],"folders":["KTMA1TYQXPCUP"],"isDeleted":false,"url":"https://www.zcool.com.cn/work/ZNTQ1MTI0ODQ=.html","annotation":"","modificationTime":1650615422558,"noThumbnail":true,"width":860,"height":542,"lastModified":1652236858727,"palettes":[{"color":[220,220,219],"ratio":82},{"color":[245,245,244],"ratio":9},{"color":[114,78,53],"ratio":4.58},{"color":[181,157,131],"ratio":1.57},{"color":[177,176,175],"ratio":0.31}]}