{"id":"L6XFWLQ81AXVB","name":"点击查看大图 [F]","size":1257532,"btime":1661780952919,"mtime":1661780952919,"ext":"jpg","tags":[],"folders":["L2FUH6TV1973M"],"isDeleted":false,"url":"https://huaban.com/pins/4811898917","annotation":"","modificationTime":1660730239232,"height":1080,"width":1920,"lastModified":1661781005814,"palettes":[{"color":[233,231,227],"ratio":41},{"color":[46,30,24],"ratio":25},{"color":[232,147,54],"ratio":14},{"color":[155,72,42],"ratio":9},{"color":[226,179,139],"ratio":2.72},{"color":[199,143,123],"ratio":2.37},{"color":[205,182,172],"ratio":1.8},{"color":[140,135,130],"ratio":1.55}]}