{"id":"LTOBREVVIIBGP","name":"videoplayback","size":1174703,"btime":1710245076770,"mtime":1710245078910,"ext":"mp4","tags":[],"folders":["LTOA7JI3607VM"],"isDeleted":false,"url":"https://rr2---sn-o097znzk.googlevideo.com/videoplayback?expire=1710273493&ei=VUPwZb_pF83e-LYPyKad4A0&ip=23.247.137.73&id=1204bdf551ce0168&itag=18&source=youtube&requiressl=yes&xpc=Eghovf3BOnoBAQ==&mh=2X&mm=31&mn=sn-o097znzk&ms=au&mv=m&mvi=2&pl=24&susc=daps&obr=googlesyndication.com&ctier=L&mime=video/mp4&vprv=1&dur=27.515&lmt=1696743214010517&mt=1710244410&txp=6310224&sparams=expire,ei,ip,id,itag,source,requiressl,xpc,susc,obr,ctier,mime,vprv,dur,lmt&sig=AJfQdSswRgIhAISHOQ6EGFiOsC0aNj6hOOPz4kU9aat6odiq4ch_uGHiAiEAosTsCIsnNfFDem04y4lUlzF33Bxe4kwVKt-vTm0iHD4=&lsparams=mh,mm,mn,ms,mv,mvi,pl&lsig=APTiJQcwRQIgLPbQAFt1N2If5vtuG-L6qJdkIy2dm-PCeXMFiV3l1GICIQDCR0lMOqu5LzdHhCXKBvJD0Pp1PNHaO7Yaw_OUBFEwYA==","annotation":"","modificationTime":1710245076763,"height":640,"width":360,"duration":27.469206,"lastModified":1710245079481,"palettes":[{"color":[81,37,12],"ratio":34},{"color":[166,114,52],"ratio":17},{"color":[243,191,92],"ratio":15},{"color":[230,164,65],"ratio":12},{"color":[138,92,37],"ratio":7},{"color":[126,70,25],"ratio":4.99},{"color":[51,18,4],"ratio":4.33},{"color":[241,224,174],"ratio":2.52},{"color":[145,120,65],"ratio":0.34}]}