{"id":"L5UMH5OKDBPBE","name":"采集23","size":519465,"btime":1658406349792,"mtime":1658406349792,"ext":"jpg","tags":[],"folders":["L5UMH5OLMRJLR"],"isDeleted":false,"url":"https://huaban.com/pins/864926795","annotation":"","modificationTime":1658383096495,"noThumbnail":true,"width":920,"height":1378,"palettes":[{"color":[30,27,24],"ratio":51},{"color":[156,143,134],"ratio":14},{"color":[101,89,81],"ratio":11},{"color":[75,65,57],"ratio":8},{"color":[72,74,77],"ratio":5},{"color":[59,62,59],"ratio":4.77},{"color":[80,86,87],"ratio":4.53},{"color":[123,124,121],"ratio":0.32}],"lastModified":1659187747355}