{"id":"L2H8FLT7CJT8R","name":"王者荣耀活动界面-514","size":885720,"btime":1651038190847,"mtime":1629276121159,"ext":"jpg","tags":[],"folders":["L2H6EFQDFOB6Z"],"isDeleted":false,"url":"","annotation":"","modificationTime":1651043104059,"noThumbnail":true,"width":1334,"height":750,"orientation":1,"lastModified":1651043118989,"palettes":[{"color":[27,57,106],"ratio":43},{"color":[15,16,20],"ratio":26},{"color":[25,33,54],"ratio":9},{"color":[184,177,167],"ratio":5},{"color":[33,82,159],"ratio":4.44},{"color":[72,119,197],"ratio":3.97},{"color":[88,119,147],"ratio":2.49},{"color":[55,89,129],"ratio":1.72},{"color":[116,88,68],"ratio":0.96},{"color":[111,165,207],"ratio":0.95}]}