{"id":"LDJTECWUWIF40","name":"title02","size":528873,"btime":1675143940327,"mtime":1675137265896,"ext":"png","tags":[],"folders":["LDJTECROH3OBJ"],"isDeleted":false,"url":"","annotation":"","modificationTime":1675143940326,"noThumbnail":true,"width":1024,"height":1024,"lastModified":1675143990236,"palettes":[{"color":[54,57,32],"ratio":42},{"color":[223,211,79],"ratio":17},{"color":[206,137,58],"ratio":15},{"color":[136,86,35],"ratio":8},{"color":[127,142,52],"ratio":5},{"color":[74,99,46],"ratio":3.89},{"color":[199,228,210],"ratio":3},{"color":[220,208,148],"ratio":2.69},{"color":[173,138,186],"ratio":0.86}]}