{"id":"LNEGQFGRI2P24","name":"开心消消乐游戏banner","size":136084,"btime":1696943220671,"mtime":1696943220672,"ext":"jpg","tags":[],"folders":["L2D5873B6M99P"],"isDeleted":false,"url":"https://huaban.com/pins/1273455594","annotation":"","modificationTime":1696588073163,"noThumbnail":true,"width":640,"height":330,"lastModified":1704722728791,"palettes":[{"color":[220,227,226],"ratio":31},{"color":[18,64,79],"ratio":13},{"color":[238,179,42],"ratio":11},{"color":[122,170,224],"ratio":9},{"color":[183,52,35],"ratio":7},{"color":[234,132,164],"ratio":7},{"color":[60,105,214],"ratio":6},{"color":[39,199,194],"ratio":4.98},{"color":[62,86,148],"ratio":2.88},{"color":[247,203,137],"ratio":2.75},{"color":[139,60,195],"ratio":2.01}]}