{"id":"KZRSCYDG7FFWZ","name":"琦特CG采集到【参考素材】油画、构图（风景）25图_花瓣","size":178087,"btime":1689072052416,"mtime":1689072052416,"ext":"jpg","tags":[],"folders":["KZRRULP8EV8S9"],"isDeleted":false,"url":"https://huaban.com/pins/3134742721/","annotation":"","modificationTime":1650612644662,"noThumbnail":true,"width":800,"height":617,"lastModified":1699862523642,"palettes":[{"color":[90,73,57],"ratio":55},{"color":[216,192,160],"ratio":18},{"color":[173,187,191],"ratio":15},{"color":[37,34,33],"ratio":5},{"color":[156,131,97],"ratio":3.74},{"color":[129,117,91],"ratio":0.89},{"color":[52,35,35],"ratio":0.82}]}