{"id":"L2H6EXIHMPT6M","name":"KSH6WNK6DOH6B","size":274613,"btime":1651039739408,"mtime":1651038497461,"ext":"jpg","tags":[],"folders":["L2H6EFQDFOB6Z"],"isDeleted":true,"url":"","annotation":"","modificationTime":1651039739408,"height":1284,"width":2778,"lastModified":1651804880655,"palettes":[{"color":[18,19,24],"ratio":57},{"color":[181,202,229],"ratio":13},{"color":[90,139,185],"ratio":10},{"color":[44,70,113],"ratio":9},{"color":[29,45,72],"ratio":7},{"color":[98,95,108],"ratio":2.91}],"deletedTime":1651804880532}