{"id":"L2E6KQ8CQCW28","name":"阴阳师界面","size":5588415,"btime":1650858575646,"mtime":1650858575683,"ext":"png","tags":[],"folders":["L2E6KPZ6KC4ZD"],"isDeleted":false,"url":"https://huaban.com/boards/63186486/","annotation":"","modificationTime":1650858582093,"height":1125,"width":2436,"lastModified":1679556892528,"palettes":[{"color":[18,15,13],"ratio":68},{"color":[206,198,186],"ratio":13},{"color":[101,86,85],"ratio":8},{"color":[181,155,120],"ratio":2.09},{"color":[178,70,65],"ratio":1.89},{"color":[182,129,46],"ratio":1.72},{"color":[164,124,110],"ratio":1.44},{"color":[59,60,102],"ratio":0.92},{"color":[104,109,153],"ratio":0.84}]}