{"id":"LCA6JSFYQB9WS","name":"Snipaste_2022-07-11_09-54-06","size":168401,"btime":1673677335579,"mtime":1673677335579,"ext":"jpg","tags":[],"folders":["L2E6UZKXFWJEW"],"isDeleted":false,"url":"","annotation":"","modificationTime":1672384496848,"noThumbnail":true,"width":1386,"height":966,"lastModified":1674998636239,"palettes":[{"color":[180,179,180],"ratio":83},{"color":[241,211,215],"ratio":7},{"color":[159,57,70],"ratio":2.29},{"color":[106,116,154],"ratio":2.11},{"color":[192,189,230],"ratio":1.62},{"color":[191,111,121],"ratio":1.39},{"color":[177,171,110],"ratio":0.8},{"color":[75,118,167],"ratio":0.68},{"color":[141,142,148],"ratio":0.46}]}