{"id":"L30A2LXP2BNYL","name":"箭头86图_@ZAKE849_花瓣","size":1204570,"btime":1652234306748,"mtime":1652234306748,"ext":"png","tags":[],"folders":["L2D5873B6M99P"],"isDeleted":false,"url":"https://huaban.com/pins/4626261429","annotation":"","modificationTime":1652194710925,"height":2000,"width":3000,"lastModified":1652234309959,"palettes":[{"color":[219,218,238],"ratio":37},{"color":[248,211,235],"ratio":14},{"color":[110,123,248],"ratio":12},{"color":[155,160,250],"ratio":8},{"color":[162,130,248],"ratio":6},{"color":[235,184,230],"ratio":6},{"color":[210,162,240],"ratio":5},{"color":[186,210,238],"ratio":5},{"color":[102,172,246],"ratio":1.78},{"color":[250,197,204],"ratio":0.51},{"color":[104,200,246],"ratio":0.34}]}