{"id":"KTMAHK21XJKSB","name":"欧美暗色卡通二次元GUI界面风格集合UI游戏UI小金狮 - 原创作品 - 站酷 ZCOOL (4)","size":335424,"btime":1631757840842,"mtime":1631757840862,"ext":"jpg","tags":[],"folders":["KTMA1TYQXPCUP"],"isDeleted":false,"url":"https://www.zcool.com.cn/work/ZNTQ1MTI0ODQ=.html","annotation":"","modificationTime":1650615422700,"height":788,"width":1560,"lastModified":1631757856668,"palettes":[{"color":[23,16,24],"ratio":79},{"color":[238,237,236],"ratio":8},{"color":[60,29,34],"ratio":5},{"color":[107,40,41],"ratio":3.31},{"color":[38,37,54],"ratio":1.53},{"color":[59,90,97],"ratio":0.4}]}