{"id":"LGRMOVAPAHTAG","name":"卡通可爱扁平自然植物动物ICON图标LOGO免抠PNG图案 AI矢量素材 (36)","size":22968,"btime":1682402877942,"mtime":1682402877942,"ext":"png","tags":[],"folders":[null,"LGRMOVAPHDM9P"],"isDeleted":false,"url":"https://huaban.com/pins/3927297159/similar","annotation":"","modificationTime":1682146662026,"noThumbnail":true,"width":1025,"height":1025,"lastModified":1682402887314,"palettes":[{"color":[236,84,59],"ratio":53},{"color":[251,163,4],"ratio":22},{"color":[212,76,60],"ratio":22},{"color":[77,72,64],"ratio":0.59},{"color":[224,84,60],"ratio":0.33}]}