{"id":"L28O28CQDR9MS","name":"chun-li (4)","size":309548,"btime":1650525155019,"mtime":1650525155028,"ext":"jpg","tags":[],"folders":["KLD5E2YKVO1LC"],"isDeleted":false,"url":"https://www.artstation.com/artwork/4XR8Q4","annotation":"","modificationTime":1650612647274,"height":2300,"width":1840,"lastModified":1650525156854,"palettes":[{"color":[4,12,49],"ratio":77},{"color":[76,76,83],"ratio":6},{"color":[96,97,106],"ratio":5},{"color":[47,48,56],"ratio":2.64},{"color":[129,127,134],"ratio":1.99},{"color":[61,59,67],"ratio":1.81},{"color":[117,114,122],"ratio":1.27},{"color":[11,10,15],"ratio":0.8},{"color":[36,34,42],"ratio":0.8},{"color":[44,52,79],"ratio":0.52},{"color":[148,151,164],"ratio":0.37}]}