{"id":"LDJW3GK6RRBQ9","name":"ta_baoleita_3_RGB_out","size":574292,"btime":1689072353105,"mtime":1689072353105,"ext":"png","tags":[],"folders":["LDJW3GIK4Y92N"],"isDeleted":false,"url":"","annotation":"","modificationTime":1675148502108,"noThumbnail":true,"width":1024,"height":1024,"lastModified":1689238650976,"palettes":[{"color":[79,80,73],"ratio":62},{"color":[226,163,88],"ratio":12},{"color":[148,131,106],"ratio":10},{"color":[15,14,13],"ratio":4.04},{"color":[107,118,118],"ratio":3.95},{"color":[122,134,128],"ratio":2.43},{"color":[41,32,24],"ratio":2.24},{"color":[137,154,164],"ratio":0.48},{"color":[162,173,164],"ratio":0.32},{"color":[93,62,25],"ratio":0.32}]}