{"id":"LHK71AQ6YYWGO","name":"【爆料来了】竹林倩影，粽香四溢！德鲁伊新皮肤，神器... - 交流专区 - 小冰冰传奇 - Powered by Discuz!","size":239006,"btime":1683873887135,"mtime":1683873887135,"ext":"jpg","tags":[],"folders":["LHK6OMBN7G5X6"],"isDeleted":false,"url":"https://huaban.com/pins/2905244945","annotation":"","modificationTime":1683873887118,"height":1801,"width":960,"lastModified":1683873887531,"palettes":[{"color":[38,40,24],"ratio":48},{"color":[131,137,81],"ratio":17},{"color":[193,189,107],"ratio":9},{"color":[92,86,45],"ratio":8},{"color":[98,116,57],"ratio":6},{"color":[66,83,45],"ratio":6},{"color":[148,168,83],"ratio":2.52},{"color":[222,223,190],"ratio":0.37}]}