{"id":"L734G9NX7O353","name":"钻石宝石PNG透明图标","size":53136,"btime":1661073798390,"mtime":1661073798386,"ext":"png","tags":["钻石"],"folders":["L2D5873B6M99P"],"isDeleted":false,"url":"https://huaban.com/pins/4926568033/","annotation":"","modificationTime":1661073798381,"noThumbnail":true,"width":256,"height":256,"palettes":[{"color":[232,248,251],"ratio":44},{"color":[154,187,213],"ratio":19},{"color":[181,209,229],"ratio":12},{"color":[200,225,244],"ratio":10},{"color":[252,251,251],"ratio":6},{"color":[212,236,251],"ratio":4.68},{"color":[178,194,226],"ratio":1.1},{"color":[222,215,240],"ratio":0.49},{"color":[162,194,243],"ratio":0.46}],"lastModified":1682428485157}