{"id":"LJ9JSR8342XKY","name":"松树叶子 松树叶 松树枝_pixian","size":472979,"btime":1687583760395,"mtime":1687583737290,"ext":"png","tags":[],"folders":["L2D5873B6M99P"],"isDeleted":false,"url":"","annotation":"","modificationTime":1687583760395,"noThumbnail":true,"width":760,"height":696,"lastModified":1697377398787,"palettes":[{"color":[104,113,34],"ratio":48},{"color":[153,152,81],"ratio":11},{"color":[136,151,55],"ratio":9},{"color":[134,133,60],"ratio":8},{"color":[162,176,91],"ratio":5},{"color":[120,124,63],"ratio":4.57},{"color":[190,176,119],"ratio":4.27},{"color":[62,72,20],"ratio":3.86},{"color":[137,144,87],"ratio":2.38},{"color":[83,75,32],"ratio":0.74},{"color":[163,158,118],"ratio":0.33}]}