{"id":"KQHTWCKXXADTN","name":"yuan-yuan-foxpart1","size":1416266,"btime":1650811849203,"mtime":1650811849203,"ext":"jpg","tags":[],"folders":["KLD5E2YKVO1LC"],"isDeleted":false,"url":"https://www.artstation.com/artwork/lxkqkz","annotation":"","modificationTime":1650612633183,"height":2633,"width":1920,"lastModified":1664004980859,"palettes":[{"color":[72,49,25],"ratio":59},{"color":[202,156,109],"ratio":16},{"color":[142,99,50],"ratio":15},{"color":[20,12,7],"ratio":4.76},{"color":[241,229,199],"ratio":1.77},{"color":[242,220,143],"ratio":1.19}]}