{"id":"LLQFG5Q3NZXU1","name":"卡通人物、动物、Q版人物_平面图片素材_褪色的微笑的画板-花瓣网","size":125089,"btime":1692957943812,"mtime":1692957943812,"ext":"jpg","tags":[],"folders":["L2D5873B6M99P"],"isDeleted":false,"url":"https://huaban.com/pins/5660683155","annotation":"","modificationTime":1692957943803,"height":1920,"width":1446,"lastModified":1692957944139,"palettes":[{"color":[209,192,205],"ratio":56},{"color":[240,234,237],"ratio":18},{"color":[221,216,236],"ratio":6},{"color":[201,122,159],"ratio":5},{"color":[243,195,206],"ratio":4},{"color":[113,58,77],"ratio":3.24},{"color":[134,193,218],"ratio":2.06},{"color":[163,191,212],"ratio":1.59},{"color":[228,188,128],"ratio":1.12},{"color":[218,166,87],"ratio":0.84}]}