{"id":"KWOEOQGQRN9BV","name":"anfei-yu-05","size":437102,"btime":1638416173573,"mtime":1638416173574,"ext":"jpg","tags":[],"folders":["KWOEFSKIPHI56"],"isDeleted":false,"url":"https://www.artstation.com/artwork/mDKPme","annotation":"","modificationTime":1650610886211,"height":1169,"width":2200,"lastModified":1638416174047,"palettes":[{"color":[232,232,232],"ratio":73},{"color":[107,106,75],"ratio":14},{"color":[184,179,144],"ratio":4.35},{"color":[192,207,99],"ratio":2.94},{"color":[168,147,87],"ratio":2.24},{"color":[193,193,190],"ratio":0.83},{"color":[205,159,97],"ratio":0.68},{"color":[170,193,205],"ratio":0.38}]}