{"id":"LDJPIGY9Z8UYC","name":"丛林宝石对战 JungleGem Match-游戏截图-GAMEUI.NET-游戏UIUX学习、交流、分享平台 (42)","size":72020,"btime":1675137325907,"mtime":1675137325926,"ext":"webp","tags":[],"folders":["LDJPIA2LP40GF"],"isDeleted":false,"url":"https://www.gameui.net/inspirationInfo/4927","annotation":"","modificationTime":1675137325787,"height":2532,"width":1170,"lastModified":1675137330141,"palettes":[{"color":[27,15,14],"ratio":49},{"color":[146,102,69],"ratio":20},{"color":[241,235,223],"ratio":13},{"color":[91,59,37],"ratio":12},{"color":[228,172,78],"ratio":2.43},{"color":[115,182,157],"ratio":0.96},{"color":[189,91,80],"ratio":0.57}]}