{"id":"L2D588PVDV6II","name":"GUICOWS SHARE：天下x天下技能图标分享","size":2867711,"btime":1624450647655,"mtime":1624450647655,"ext":"jpg","tags":[],"folders":["L2D5873BRDVGR"],"isDeleted":false,"url":"https://huaban.com/pins/3477989749/","annotation":"","modificationTime":1650795854444,"height":3210,"width":1600,"orientation":1,"lastModified":1624450647919,"palettes":[{"color":[49,49,53],"ratio":59},{"color":[210,195,180],"ratio":11},{"color":[125,88,92],"ratio":6},{"color":[84,190,192],"ratio":5},{"color":[49,74,123],"ratio":3.42},{"color":[79,117,174],"ratio":3.15},{"color":[91,57,57],"ratio":2.54},{"color":[43,121,113],"ratio":2.23},{"color":[216,140,45],"ratio":2.19},{"color":[30,89,79],"ratio":1.38},{"color":[184,65,46],"ratio":1.19}]}