{"id":"LKGL1MVXR7VYO","name":"图片_插画】Q版原画场景及部件图片素材-花瓣网","size":60499,"btime":1690206566752,"mtime":1690206566752,"ext":"png","tags":[],"folders":["L2D5873B6M99P"],"isDeleted":false,"url":"https://huaban.com/pins/3160775861","annotation":"","modificationTime":1690185899805,"noThumbnail":true,"width":302,"height":323,"lastModified":1697075921994,"palettes":[{"color":[203,218,248],"ratio":37},{"color":[46,85,67],"ratio":29},{"color":[139,178,106],"ratio":12},{"color":[151,145,228],"ratio":6},{"color":[104,154,201],"ratio":4},{"color":[149,180,232],"ratio":4},{"color":[201,228,158],"ratio":3.2},{"color":[96,96,180],"ratio":2.2},{"color":[136,87,90],"ratio":0.33}]}