{"id":"L2FZDEXZLJEJ8","name":"resize,m_lfit,w_1920","size":141052,"btime":1622515696781,"mtime":1622515696781,"ext":"jpg","tags":[],"folders":["L2FZDBESXKSML"],"isDeleted":false,"url":"https://gameui.net/articleDetails/2105","annotation":"","modificationTime":1650967416679,"height":960,"width":1920,"lastModified":1622515697257,"palettes":[{"color":[51,47,47],"ratio":89},{"color":[121,107,85],"ratio":3.35},{"color":[87,76,60],"ratio":2.19},{"color":[74,77,61],"ratio":1.19},{"color":[182,146,85],"ratio":1.1},{"color":[93,88,87],"ratio":0.74},{"color":[137,133,127],"ratio":0.71},{"color":[32,27,8],"ratio":0.52},{"color":[99,103,89],"ratio":0.43}]}