{"id":"LIO9SBNW6RTJF","name":"查看图片","size":4485253,"btime":1686297154365,"mtime":1686297154367,"ext":"jpg","tags":[],"folders":["KW1QIKS19IQJE","L2E6UZKXWNVFT"],"isDeleted":false,"url":"https://huaban.com/pins/5532745579?modalImg=https%3A%2F%2Fgd-hbimg.huaban.com%2Fd349f26723bda7833f6c7c3fcaa48b9f53d379a2447085-xschsT","annotation":"","modificationTime":1686297154316,"height":9136,"width":2560,"palettes":[{"color":[42,36,36],"ratio":53,"$$hashKey":"object:8870"},{"color":[193,171,144],"ratio":18,"$$hashKey":"object:8871"},{"color":[129,105,84],"ratio":14,"$$hashKey":"object:8872"},{"color":[87,66,54],"ratio":8,"$$hashKey":"object:8873"},{"color":[84,113,95],"ratio":1.88,"$$hashKey":"object:8874"},{"color":[213,221,231],"ratio":1.15,"$$hashKey":"object:8875"},{"color":[138,168,163],"ratio":0.74,"$$hashKey":"object:8876"},{"color":[76,79,118],"ratio":0.43,"$$hashKey":"object:8877"},{"color":[183,130,61],"ratio":0.39,"$$hashKey":"object:8878"},{"color":[116,123,180],"ratio":0.37,"$$hashKey":"object:8879"}],"lastModified":1686297173355}