{"id":"L6OUOGRXPMM51","name":"倒退式进步和稳定性进步的PK (33)","size":71462,"btime":1661066750470,"mtime":1661066750470,"ext":"jpg","tags":[],"folders":["KTMA1TYQXPCUP"],"isDeleted":false,"url":"https://mp.weixin.qq.com/s/vvJrBsMFtMsLJARQCXq0wA","annotation":"","modificationTime":1660210857861,"noThumbnail":true,"width":1080,"height":545,"lastModified":1661066767789,"palettes":[{"color":[52,43,44],"ratio":73},{"color":[239,236,232],"ratio":9},{"color":[121,92,73],"ratio":5},{"color":[90,67,54],"ratio":5},{"color":[185,130,93],"ratio":2.9},{"color":[92,83,80],"ratio":2.29},{"color":[127,116,114],"ratio":1.24}]}