{"id":"L2H8FLT7583PB","name":"王者荣耀活动界面-525","size":948564,"btime":1651038191031,"mtime":1629276126124,"ext":"jpg","tags":[],"folders":["L2H6EFQDFOB6Z"],"isDeleted":true,"url":"","annotation":"","modificationTime":1651043103956,"noThumbnail":true,"width":1334,"height":750,"orientation":1,"lastModified":1651804849083,"palettes":[{"color":[32,61,93],"ratio":28},{"color":[225,214,194],"ratio":15},{"color":[145,119,96],"ratio":12},{"color":[63,107,148],"ratio":11},{"color":[102,76,58],"ratio":10},{"color":[143,197,183],"ratio":7},{"color":[29,39,39],"ratio":7},{"color":[97,138,73],"ratio":3.31},{"color":[81,145,189],"ratio":1.32},{"color":[211,142,95],"ratio":0.54},{"color":[180,110,88],"ratio":0.48}],"deletedTime":1651804848307}