{"id":"LILC6UXA8YFW5","name":"screenshot","size":450542,"btime":1686119793178,"mtime":1686119793178,"ext":"jpg","tags":[],"folders":["LMFOMTB76KZZT"],"isDeleted":false,"url":"https://huaban.com/pins/5500048552","annotation":"","modificationTime":1686119793166,"height":1300,"width":1950,"lastModified":1694485115815,"palettes":[{"color":[25,37,47],"ratio":78},{"color":[221,226,229],"ratio":14},{"color":[114,121,128],"ratio":3.91},{"color":[69,77,86],"ratio":2.25},{"color":[139,146,157],"ratio":0.42}]}