{"id":"LCA8459SCK6SR","name":"3Monkeys_Logo","size":290573,"btime":1673677336688,"mtime":1673677336688,"ext":"png","tags":[],"folders":["LCKABRN9VHN2Q"],"isDeleted":false,"url":"","annotation":"","modificationTime":1672387127365,"width":683,"height":309,"noThumbnail":true,"lastModified":1677850436109,"palettes":[{"color":[80,58,23],"ratio":39},{"color":[51,196,236],"ratio":28},{"color":[243,126,140],"ratio":13},{"color":[241,248,249],"ratio":8},{"color":[72,81,99],"ratio":4.62},{"color":[242,220,11],"ratio":3.69},{"color":[149,123,89],"ratio":0.82}]}