{"id":"LDJTCIZ66KUR3","name":"Common_Icon_Menu_T_05","size":1800,"btime":1675137274795,"mtime":1675137274796,"ext":"png","tags":[],"folders":["LDJTBC7CU1QRJ"],"isDeleted":true,"url":"","annotation":"","modificationTime":1675143768418,"noThumbnail":true,"width":52,"height":52,"palettes":[{"color":[252,252,252],"ratio":93},{"color":[218,218,218],"ratio":1.72},{"color":[236,236,236],"ratio":1.72},{"color":[244,244,244],"ratio":1.53},{"color":[228,228,228],"ratio":1.34}],"deletedTime":1675143816450,"lastModified":1675143816618}