{"id":"LG6B8QHCP1DD0","name":"2023-04-07 16 30 35","size":845917,"btime":1680856235226,"mtime":1680856235569,"ext":"png","tags":[],"folders":["LGG6QXGM18XCZ"],"isDeleted":false,"url":"","annotation":"","modificationTime":1680857643985,"noThumbnail":true,"width":1253,"height":710,"lastModified":1681454760869,"palettes":[{"color":[227,233,222],"ratio":45},{"color":[149,153,124],"ratio":13},{"color":[188,193,164],"ratio":12},{"color":[70,81,75],"ratio":9},{"color":[144,165,166],"ratio":7},{"color":[179,198,187],"ratio":7},{"color":[161,148,73],"ratio":2.04},{"color":[166,163,162],"ratio":0.34}]}