{"id":"LH31L25NCHEE9","name":"蜂蜜浏览器_paytable2-gigapixel-art-scale-4_00x","size":1066521,"btime":1682836796021,"mtime":1682836796081,"ext":"png","tags":[],"folders":[],"isDeleted":false,"url":"","annotation":"","modificationTime":1682836806464,"noThumbnail":true,"width":1024,"height":1024,"lastModified":1682836806555,"palettes":[{"color":[240,213,38],"ratio":25},{"color":[240,198,224],"ratio":21},{"color":[243,234,145],"ratio":12},{"color":[120,42,29],"ratio":11},{"color":[180,106,47],"ratio":11},{"color":[227,18,238],"ratio":8},{"color":[215,153,26],"ratio":5},{"color":[219,30,84],"ratio":2.11},{"color":[109,93,89],"ratio":0.8},{"color":[167,155,48],"ratio":0.59}]}