{"id":"L2H8FLT8PZFG5","name":"王者创意互动周好礼来袭 云中君纤云弄巧限时秒杀-2","size":342315,"btime":1651038190337,"mtime":1629276114507,"ext":"png","tags":[],"folders":["L2H6EFQDFOB6Z"],"isDeleted":false,"url":"","annotation":"","modificationTime":1651043112369,"noThumbnail":true,"width":554,"height":319,"lastModified":1651043132768,"palettes":[{"color":[25,27,33],"ratio":45},{"color":[215,203,207],"ratio":22},{"color":[132,173,185],"ratio":8},{"color":[126,111,109],"ratio":6},{"color":[104,119,171],"ratio":5},{"color":[220,185,127],"ratio":4.52},{"color":[57,76,113],"ratio":2.64},{"color":[73,100,113],"ratio":2.54},{"color":[211,127,125],"ratio":1.6},{"color":[191,148,85],"ratio":0.47}]}