{"id":"LDJTECWPB2IG2","name":"Common_Icon_Gold_02","size":5395,"btime":1675174794434,"mtime":1675174794434,"ext":"png","tags":[],"folders":["LDJTECR1UHOT7"],"isDeleted":false,"url":"","annotation":"","modificationTime":1675143939538,"noThumbnail":true,"width":50,"height":53,"lastModified":1708419957984,"palettes":[{"color":[248,185,40],"ratio":48},{"color":[84,43,8],"ratio":11},{"color":[220,117,22],"ratio":9},{"color":[251,249,180],"ratio":8},{"color":[249,232,123],"ratio":7},{"color":[243,199,82],"ratio":5},{"color":[154,68,10],"ratio":3.31},{"color":[251,233,86],"ratio":2.53},{"color":[193,81,14],"ratio":2.23}]}