{"id":"LMX210RS5QPJO","name":"Family Thanksgiving - Illustration","size":203458,"btime":1697162182602,"mtime":1697162182602,"ext":"jpg","tags":[],"folders":["L2D5873B6M99P"],"isDeleted":false,"url":"https://www.pinterest.com/pin/400327854384168839/","annotation":"","modificationTime":1695535448104,"height":1200,"width":1801,"lastModified":1697162189270,"palettes":[{"color":[238,234,219],"ratio":40},{"color":[219,106,54],"ratio":22},{"color":[186,147,99],"ratio":14},{"color":[106,92,100],"ratio":8},{"color":[241,188,154],"ratio":5},{"color":[90,178,191],"ratio":2.05},{"color":[223,87,87],"ratio":1.82},{"color":[72,64,58],"ratio":1.44},{"color":[169,137,164],"ratio":1.41},{"color":[144,198,145],"ratio":0.96},{"color":[202,207,50],"ratio":0.41}]}