{"id":"L2FZDF50VYCAS","name":"鬼船劫","size":32468,"btime":1624864304691,"mtime":1624864304691,"ext":"png","tags":[],"folders":["L2FZDBESEQRYU"],"isDeleted":false,"url":"https://huaban.com/pins/2704661600/","annotation":"","modificationTime":1650967416997,"noThumbnail":true,"width":200,"height":200,"lastModified":1624864304770,"palettes":[{"color":[71,42,39],"ratio":39},{"color":[145,103,58],"ratio":19},{"color":[218,200,174],"ratio":13},{"color":[19,16,17],"ratio":8},{"color":[106,90,64],"ratio":6},{"color":[92,93,112],"ratio":5},{"color":[199,164,59],"ratio":2.99},{"color":[114,111,95],"ratio":2.62},{"color":[172,168,161],"ratio":0.75}]}