{"id":"LDJW3GK9EF21Y","name":"jia2","size":9226,"btime":1675144880643,"mtime":1675144880646,"ext":"png","tags":[],"folders":["LDJW3GIK4Y92N"],"isDeleted":false,"url":"","annotation":"","modificationTime":1675148528612,"noThumbnail":true,"width":128,"height":128,"lastModified":1675148562872,"palettes":[{"color":[252,251,248],"ratio":52},{"color":[250,131,8],"ratio":19},{"color":[248,231,155],"ratio":11},{"color":[251,245,187],"ratio":7},{"color":[248,180,76],"ratio":3.47},{"color":[248,196,94],"ratio":2.26},{"color":[230,196,118],"ratio":0.85},{"color":[248,214,119],"ratio":0.56},{"color":[252,168,48],"ratio":0.39},{"color":[236,212,180],"ratio":0.34}]}