{"id":"LE8715LN1U9E5","name":"新年春节背景PNG图片","size":675633,"ext":"png","tags":["图案","国风","纹理"],"folders":[],"isDeleted":true,"url":"https://huaban.com/pins/3707152449/","annotation":"","modificationTime":1676617939416,"height":1845,"width":2123,"lastModified":1678175388217,"palettes":[{"color":[162,118,58],"ratio":44},{"color":[161,117,68],"ratio":33},{"color":[172,117,61],"ratio":9},{"color":[161,118,76],"ratio":6},{"color":[148,122,60],"ratio":1.41},{"color":[164,108,63],"ratio":1.16},{"color":[158,121,86],"ratio":1.03},{"color":[181,113,63],"ratio":0.69},{"color":[162,119,44],"ratio":0.51}],"mtime":1654564511353,"btime":1625646956897,"deletedTime":1678175388110}