{"id":"LE2K7P1HEMTCO","name":"10664","size":22245,"btime":1675822145837,"mtime":1675822145840,"ext":"png","tags":[],"folders":["LE2K6F4TJARST"],"isDeleted":false,"url":"","annotation":"","modificationTime":1676277282459,"noThumbnail":true,"width":120,"height":120,"lastModified":1676277282871,"palettes":[{"color":[179,71,45],"ratio":30},{"color":[250,215,176],"ratio":23},{"color":[233,94,58],"ratio":16},{"color":[243,142,97],"ratio":10},{"color":[152,24,17],"ratio":7},{"color":[130,58,37],"ratio":7},{"color":[103,36,26],"ratio":6}]}