{"id":"LCA8459ZFWF72","name":"circus-delight_l_q","size":7456,"btime":1599418580000,"mtime":1599418580000,"ext":"png","tags":[],"folders":["LCA845A0WB2X1"],"isDeleted":false,"url":"","annotation":"","modificationTime":1672387143514,"width":294,"height":333,"noThumbnail":true,"lastModified":1625824737636,"palettes":[{"color":[234,119,48],"ratio":26},{"color":[158,27,15],"ratio":21},{"color":[240,148,92],"ratio":13},{"color":[249,223,63],"ratio":10},{"color":[247,181,69],"ratio":10},{"color":[194,81,43],"ratio":6},{"color":[245,154,46],"ratio":6},{"color":[168,32,28],"ratio":2.07},{"color":[196,108,40],"ratio":0.83}]}