{"id":"L2H9P4XC9BWXA","name":"忘川风华录-游戏截图-GAMEUI.NET-游戏UIUX学习、交流、分享平台 (179)","size":191204,"btime":1651045225013,"mtime":1651045225024,"ext":"jpg","tags":[],"folders":["L2H9P1TO3UML4"],"isDeleted":false,"url":"https://gameui.net/inspirationInfo/2150","annotation":"","modificationTime":1651045224203,"height":960,"width":1920,"lastModified":1651045263615,"palettes":[{"color":[138,99,65],"ratio":53},{"color":[92,65,45],"ratio":10},{"color":[68,47,32],"ratio":7},{"color":[175,126,80],"ratio":6},{"color":[225,207,182],"ratio":5},{"color":[175,148,128],"ratio":5},{"color":[208,163,134],"ratio":3.73},{"color":[203,186,146],"ratio":3.44},{"color":[180,143,99],"ratio":3.29}]}