{"id":"L6X9E88OJNZ66","name":"海岛纪元游戏截图","size":399503,"btime":1661780952814,"mtime":1661780952814,"ext":"jpg","tags":["宣传"],"folders":["L6X8Z31UKLU27"],"isDeleted":false,"url":"https://www.taptap.com/app/91850","annotation":"","modificationTime":1660719304248,"height":1080,"width":1920,"palettes":[{"color":[203,222,222],"ratio":29},{"color":[179,80,58],"ratio":17},{"color":[191,170,105],"ratio":15},{"color":[224,208,145],"ratio":11},{"color":[121,179,210],"ratio":10},{"color":[79,145,173],"ratio":9},{"color":[153,90,83],"ratio":2.85},{"color":[67,57,47],"ratio":2.09},{"color":[164,149,159],"ratio":1.46},{"color":[196,188,54],"ratio":0.47},{"color":[66,66,122],"ratio":0.4}],"lastModified":1661781003924}